ethdatabase/__init__.py
ethdatabase/main.py
ethdatabase-1.2.1.dist-info/METADATA
ethdatabase-1.2.1.dist-info/WHEEL
ethdatabase-1.2.1.dist-info/top_level.txt
ethdatabase-1.2.1.dist-info/RECORD
